pfb/__init__.py
pfb/deconv/__init__.py
pfb/deconv/clark.py
pfb/deconv/hogbom.py
pfb/deconv/nnls.py
pfb/deconv/sara.py
pfb/operators/__init__.py
pfb/operators/energy.py
pfb/operators/fft.py
pfb/operators/gauss.py
pfb/operators/gridder.py
pfb/operators/hessian.py
pfb/operators/mask.py
pfb/operators/psf.py
pfb/operators/psi.py
pfb/operators/psi2.py
pfb/opt/__init__.py
pfb/opt/fista.py
pfb/opt/pcg.py
pfb/opt/power_method.py
pfb/opt/primal_dual.py
pfb/parser/__init__.py
pfb/parser/cgopts.yml
pfb/parser/degrid.yaml
pfb/parser/dist.yml
pfb/parser/fluxtractor.yaml
pfb/parser/grid.yaml
pfb/parser/gridding.yml
pfb/parser/hci.yaml
pfb/parser/init.yaml
pfb/parser/kclean.yaml
pfb/parser/model2comps.yaml
pfb/parser/out.yml
pfb/parser/pdopts.yml
pfb/parser/pmopts.yml
pfb/parser/restore.yaml
pfb/parser/sara.yaml
pfb/parser/schemas.py
pfb/parser/smoovie.yaml
pfb/parser/spotless.yaml
pfb/parser/uncabbedcabs.yml
pfb/prox/__init__.py
pfb/prox/prox2.py
pfb/prox/prox_21.py
pfb/prox/prox_21m.py
pfb/stimela_cabs.yml
pfb/utils/__init__.py
pfb/utils/astrometry.py
pfb/utils/beam.py
pfb/utils/correlations.py
pfb/utils/dist.py
pfb/utils/fits.py
pfb/utils/logging.py
pfb/utils/misc.py
pfb/utils/modelspec.py
pfb/utils/naming.py
pfb/utils/restoration.py
pfb/utils/spi.py
pfb/utils/stokes.py
pfb/utils/stokes2im.py
pfb/utils/stokes2vis.py
pfb/utils/transients.py
pfb/utils/weighting.py
pfb/wavelets/__init__.py
pfb/wavelets/wavelets.py
pfb/wavelets/wavelets_jsk.py
pfb/workers/__init__.py
pfb/workers/degrid.py
pfb/workers/fluxtractor.py
pfb/workers/grid.py
pfb/workers/hci.py
pfb/workers/init.py
pfb/workers/kclean.py
pfb/workers/main.py
pfb/workers/model2comps.py
pfb/workers/restore.py
pfb/workers/sara.py
pfb/workers/smoovie.py
pfb/workers/spotless.py
pfb_imaging-0.0.8.dist-info/METADATA
pfb_imaging-0.0.8.dist-info/WHEEL
pfb_imaging-0.0.8.dist-info/entry_points.txt
pfb_imaging-0.0.8.dist-info/licenses/LICENSE
pfb_imaging-0.0.8.dist-info/RECORD
