Metadata-Version: 2.4
Name: pfb-imaging
Version: 0.0.8
Summary: Radio interferometric imaging suite based on a preconditioned forward-backward approach
License: MIT
License-File: LICENSE
Author: Landman Bester
Author-email: lbester@sarao.ac.za
Requires-Python: >=3.10,<3.13
Classifier: Development Status :: 4 - Beta
Classifier: Intended Audience :: Science/Research
Classifier: License :: OSI Approved :: MIT License
Classifier: Operating System :: POSIX :: Linux
Classifier: Programming Language :: Python :: 3
Classifier: Programming Language :: Python :: 3.10
Classifier: Programming Language :: Python :: 3.11
Classifier: Programming Language :: Python :: 3.12
Classifier: Topic :: Scientific/Engineering :: Astronomy
Requires-Dist: Click (>=8.1)
Requires-Dist: PyWavelets (>=1.7.0)
Requires-Dist: bokeh (>=3.1.0)
Requires-Dist: codex-africanus[astropy,dask,python-casacore,scipy] (>=0.4.2)
Requires-Dist: dask-ms[s3,xarray,zarr] (>=0.2.23)
Requires-Dist: ducc0 (>=0.35.0)
Requires-Dist: jax[cpu] (>=0.4.31)
Requires-Dist: katbeam (>=0.1)
Requires-Dist: lz4 (>=4.3.3)
Requires-Dist: matplotlib (>=3.9.2)
Requires-Dist: numexpr (>=2.10.1)
Requires-Dist: psutil (>=5.9.8)
Requires-Dist: pytest (>=8.0.0)
Requires-Dist: ray[default] (>=2.48.0,<3.0.0)
Requires-Dist: regions (>=0.9)
Requires-Dist: reproject (>=0.14.1)
Requires-Dist: rich (>=13.0.0)
Requires-Dist: scikit-image (>=0.24.0)
Requires-Dist: stimela (>=2.0.2)
Requires-Dist: streamjoy (>=0.0.8)
Requires-Dist: sympy (>=1.9)
Requires-Dist: tbb (>=2021.13.1)
